ccd_cli/__init__.py
ccd_cli/__main__.py
ccd_cli/cli.py
ccd_cli/commands/__init__.py
ccd_cli/commands/ai_context.py
ccd_cli/commands/coverage.py
ccd_cli/commands/freshness.py
ccd_cli/commands/generate.py
ccd_cli/commands/health.py
ccd_cli/commands/init.py
ccd_cli/commands/methodology.py
ccd_cli/commands/monitor.py
ccd_cli/commands/pack.py
ccd_cli/commands/prepare_context.py
ccd_cli/commands/quality.py
ccd_cli/commands/validate.py
ccd_cli/commands/version.py
ccd_cli/core/__init__.py
ccd_cli/core/codemap.py
ccd_cli/core/context_card.py
ccd_cli/core/module_index.py
ccd_cli/core/project.py
ccd_cli/utils/__init__.py
ccd_cli/utils/config.py
ccd_cli/utils/errors.py
ccd_cli/utils/file_analyzer.py
ccd_cli/utils/git_analyzer.py
ccd_cli/utils/metrics_calculator.py
ccd_cli-0.1.0.dist-info/licenses/LICENSE
ccd_cli-0.1.0.dist-info/METADATA
ccd_cli-0.1.0.dist-info/WHEEL
ccd_cli-0.1.0.dist-info/entry_points.txt
ccd_cli-0.1.0.dist-info/top_level.txt
ccd_cli-0.1.0.dist-info/RECORD
