Metadata-Version: 2.4
Name: ccd-cli
Version: 0.1.0
Summary: CLI tools for Continuous Context Documentation (CCD)
Author-email: Yegor Ferrieres aka Egor Borodavko <yegor@martlive.ai>
Maintainer-email: Yegor Ferrieres aka Egor Borodavko <yegor@martlive.ai>
License: MIT
Project-URL: Homepage, https://github.com/yegorferrieres/ccd-ai
Project-URL: Documentation, https://github.com/yegorferrieres/ccd-ai/tree/main/docs
Project-URL: Repository, https://github.com/yegorferrieres/ccd-ai
Project-URL: Bug Tracker, https://github.com/yegorferrieres/ccd-ai/issues
Keywords: ccd,documentation,context,rag,software-development,ai-context,code-integration
Classifier: Development Status :: 4 - Beta
Classifier: Intended Audience :: Developers
Classifier: License :: OSI Approved :: MIT License
Classifier: Operating System :: OS Independent
Classifier: Programming Language :: Python :: 3
Classifier: Programming Language :: Python :: 3.8
Classifier: Programming Language :: Python :: 3.9
Classifier: Programming Language :: Python :: 3.10
Classifier: Programming Language :: Python :: 3.11
Classifier: Programming Language :: Python :: 3.12
Classifier: Topic :: Software Development :: Documentation
Classifier: Topic :: Software Development :: Libraries :: Python Modules
Classifier: Topic :: Software Development :: Code Generators
Classifier: Topic :: Text Processing :: Markup
Requires-Python: >=3.8
License-File: LICENSE
Requires-Dist: click>=8.1.0
Requires-Dist: pyyaml>=6.0
Requires-Dist: jsonschema>=4.20.0
Requires-Dist: rich>=13.7.0
Requires-Dist: pathlib2>=2.3.7
Requires-Dist: gitpython>=3.1.0
Requires-Dist: watchdog>=3.0.0
Requires-Dist: colorama>=0.4.6
Requires-Dist: tabulate>=0.9.0
Requires-Dist: jinja2>=3.1.0
Requires-Dist: markdown>=3.5.0
Provides-Extra: dev
Requires-Dist: pytest>=7.0.0; extra == "dev"
Requires-Dist: pytest-cov>=4.0.0; extra == "dev"
Requires-Dist: black>=23.0.0; extra == "dev"
Requires-Dist: isort>=5.12.0; extra == "dev"
Requires-Dist: flake8>=6.0.0; extra == "dev"
Requires-Dist: mypy>=1.0.0; extra == "dev"
Requires-Dist: pre-commit>=3.0.0; extra == "dev"
Dynamic: license-file
